odoo/addons/stock_picking_show_backorder/README.rst
odoo/addons/stock_picking_show_backorder/__init__.py
odoo/addons/stock_picking_show_backorder/__manifest__.py
odoo/addons/stock_picking_show_backorder/i18n/de.po
odoo/addons/stock_picking_show_backorder/i18n/es.po
odoo/addons/stock_picking_show_backorder/i18n/fr.po
odoo/addons/stock_picking_show_backorder/i18n/it.po
odoo/addons/stock_picking_show_backorder/i18n/nl_NL.po
odoo/addons/stock_picking_show_backorder/i18n/pt.po
odoo/addons/stock_picking_show_backorder/i18n/pt_BR.po
odoo/addons/stock_picking_show_backorder/models/__init__.py
odoo/addons/stock_picking_show_backorder/models/stock.py
odoo/addons/stock_picking_show_backorder/views/stock_view.xml
odoo11_addon_stock_picking_show_backorder-11.0.1.0.0.dist-info/DESCRIPTION.rst
odoo11_addon_stock_picking_show_backorder-11.0.1.0.0.dist-info/METADATA
odoo11_addon_stock_picking_show_backorder-11.0.1.0.0.dist-info/RECORD
odoo11_addon_stock_picking_show_backorder-11.0.1.0.0.dist-info/WHEEL
odoo11_addon_stock_picking_show_backorder-11.0.1.0.0.dist-info/metadata.json
odoo11_addon_stock_picking_show_backorder-11.0.1.0.0.dist-info/top_level.txt
